erelim/__init__.py
erelim/main.py
erelim-0.1.0.dist-info/METADATA
erelim-0.1.0.dist-info/WHEEL
erelim-0.1.0.dist-info/RECORD
