Metadata-Version: 2.1
Name: erelim
Version: 0.1.0
Summary: 
Author: kaliv0
Author-email: kaloyan.ivanov88@gmail.com
Requires-Python: >=3.12,<4.0
Classifier: Programming Language :: Python :: 3
Requires-Dist: twine (>=5.1.1,<6.0.0)
